{
  "commits": [
    {
      "id": "09e2ffb527999636fdb0c0ed00708d876f094385",
      "date": 1430150421,
      "n_files": 0
    },
    {
      "id": "a17124c3f11cdd8344ca60ce7a79a037e98d7238",
      "date": 1430150538,
      "n_files": 0
    },
    {
      "id": "4a57373a659247137105ac35fdddaacad5e3ae41",
      "date": 1430150886,
      "n_files": 0
    },
    {
      "id": "a6201de9d02ddc852d413523642cc1bb4b51f557",
      "date": 1430150944,
      "n_files": 0
    },
    {
      "id": "1b341fe7fbb979f1ead671ed41f488c792f6d4ec",
      "date": 1430152483,
      "n_files": 0
    },
    {
      "id": "87ce01b43b9c96631484c690214fc89ba88a5690",
      "date": 1431888488,
      "n_files": 0
    },
    {
      "id": "edb434c788182682668c8a7c3c695bbab4f1e0b3",
      "date": 1431888549,
      "n_files": 0
    },
    {
      "id": "089df6725aa7d61e140b7dd46b1e887d21852a82",
      "date": 1431888656,
      "n_files": 0
    },
    {
      "id": "baa84a750834e7c23c18ae844ecad777e0718275",
      "date": 1433676535,
      "n_files": 0
    },
    {
      "id": "c9053edb96f531b67102e51ed44b5f6de0bf3a3f",
      "date": 1448471535,
      "n_files": 0
    },
    {
      "id": "4a01fb77a5f3b09fc6318456a658a9de05810206",
      "date": 1500893495,
      "extension_function": 4,
      "lambda": 17,
      "when_expr": 5,
      "inference": 40,
      "property_delegation": 2,
      "coroutine": 2,
      "func_with_default_value": 1,
      "string_template": 2,
      "n_files": 5
    },
    {
      "id": "c095e7c162adea422904de95de1271cea99d3e8b",
      "date": 1500893752,
      "extension_function": 4,
      "lambda": 17,
      "when_expr": 5,
      "inference": 40,
      "property_delegation": 2,
      "coroutine": 2,
      "func_with_default_value": 1,
      "string_template": 2,
      "n_files": 5
    },
    {
      "id": "c51a096ef8ff4ef2d669e50e77cde47f24694971",
      "date": 1500893986,
      "extension_function": 4,
      "lambda": 17,
      "when_expr": 5,
      "inference": 40,
      "property_delegation": 2,
      "coroutine": 2,
      "func_with_default_value": 1,
      "string_template": 2,
      "n_files": 5
    },
    {
      "id": "0a038f98bf735ef0166f02b838d0d0f3c4dc3ed4",
      "date": 1500894166,
      "extension_function": 4,
      "lambda": 17,
      "when_expr": 5,
      "inference": 40,
      "property_delegation": 2,
      "coroutine": 2,
      "func_with_default_value": 1,
      "string_template": 2,
      "n_files": 5
    },
    {
      "id": "02a0d9da4bb13210b7bd7bb5198d39d2b1fb7a70",
      "date": 1509461907,
      "extension_function": 4,
      "lambda": 17,
      "when_expr": 6,
      "inference": 45,
      "property_delegation": 2,
      "coroutine": 2,
      "func_with_default_value": 1,
      "string_template": 2,
      "n_files": 6
    },
    {
      "id": "b59041001704ec477599a98261d28292c181b23b",
      "date": 1509550943,
      "extension_function": 4,
      "lambda": 19,
      "when_expr": 5,
      "inference": 48,
      "property_delegation": 2,
      "destructuring_declaration": 1,
      "coroutine": 2,
      "safe_call": 1,
      "func_with_default_value": 1,
      "string_template": 2,
      "n_files": 6
    }
  ]
}
